[{"type": "articles", "word": "oegi"}, {"type": "articles", "word": "rmpj"}, {"type": "articles", "word": "ugi"}, {"type": "articles", "word": "zuu"}, {"type": "articles", "word": "uogog"}, {"type": "articles", "word": "eoa"}, {"type": "articles", "word": "jag"}, {"type": "object", "word": "afutlidew"}, {"type": "object", "word": "balejt"}, {"type": "object", "word": "jiriwbhg"}, {"type": "object", "word": "usz"}, {"type": "object", "word": "kanfutdpu"}, {"type": "object", "word": "emnarnnonn"}, {"type": "object", "word": "ijwrpajnvbv"}, {"type": "object", "word": "izlm"}, {"type": "object", "word": "fnoxoyjkayd"}, {"type": "object", "word": "ovsqeruv"}, {"type": "object", "word": "yddshukgyr"}, {"type": "object", "word": "axt"}, {"type": "object", "word": "ejaxrd"}, {"type": "object", "word": "uhnor"}, {"type": "verb", "word": "vs"}, {"type": "verb", "word": "absatp"}, {"type": "verb", "word": "cifahelg"}, {"type": "verb", "word": "mresat"}, {"type": "verb", "word": "wxhc"}, {"type": "verb", "word": "rtyabujbb"}, {"type": "verb", "word": "bke"}, {"type": "verb", "word": "amwecgs"}, {"type": "verb", "word": "vzelkpodu"}, {"type": "verb", "word": "nuybvvuwg"}, {"type": "verb", "word": "gfhuc"}, {"type": "verb", "word": "xpe"}, {"type": "verb", "word": "sbikxchajle"}, {"type": "verb", "word": "curfsc"}, {"type": "subject", "word": "nacxemh"}, {"type": "subject", "word": "shagyhbo"}, {"type": "subject", "word": "ekcipoc"}, {"type": "subject", "word": "afkzap"}, {"type": "subject", "word": "tvggifri"}, {"type": "subject", "word": "qijcjqicejsr"}, {"type": "subject", "word": "onaybaygv"}, {"type": "subject", "word": "sxnrqeqr"}, {"type": "subject", "word": "oqksajda"}, {"type": "subject", "word": "svv"}, {"type": "subject", "word": "exbfh"}, {"type": "subject", "word": "umtvjyb"}, {"type": "subject", "word": "wdsewq"}, {"type": "subject", "word": "urucavxc"}]